onboot/__init__.py
onboot/darwin.py
onboot/linux.py
onboot/windows.py
onboot-1.0.2.dist-info/METADATA
onboot-1.0.2.dist-info/WHEEL
onboot-1.0.2.dist-info/licenses/LICENSE
onboot-1.0.2.dist-info/RECORD
