Metadata-Version: 2.4
Name: onboot
Version: 1.0.2
Summary: Cross-platform autostart installer library for Python
Project-URL: Homepage, https://github.com/nbdy/onboot
Project-URL: Repository, https://github.com/nbdy/onboot.git
Project-URL: Issues, https://github.com/nbdy/onboot/issues
Author: nbdy
Maintainer: nbdy
License: MIT License
License-File: LICENSE
Keywords: autostart,boot,cross-platform,persistence,startup
Classifier: Development Status :: 4 - Beta
Classifier: License :: OSI Approved :: MIT License
Classifier: Programming Language :: Python :: 3.11
Classifier: Programming Language :: Python :: 3.12
Requires-Python: >=3.8
